<?xml version="1.0" encoding="UTF-8" standalone="yes"?><info><interfaceInfo><version>2.27</version><date>202007080807</date></interfaceInfo><chargePointsInfo><chargePointInfo><id>BEB2CB85-33DB-4261-8DD7-875E978E45DB</id><name>EVSE</name><description></description><type>CCL1ENGINE</type><typeDescription>CCL1 Engine</typeDescription><manufacturer>Circontrol S.A.</manufacturer><vendor>Circontrol</vendor><model>R50 CCS CHA T2C63</model><platform><version>2.15.4-rc2</version></platform><serialNumber>12123019510002</serialNumber><virtual>T</virtual><chooseMethod>6</chooseMethod><allowSocketBrothersOnReserve>F</allowSocketBrothersOnReserve><evConnectionTimeout>65</evConnectionTimeout><reader>37C314E9-6C0D-4C7C-BAB0-322771539396</reader><paymentTerminalManagementSystem>F</paymentTerminalManagementSystem><plugsNumber>2</plugsNumber><plugs><id>DD51A738-CC97-4C29-BC02-5A281A5F141C</id><id>DD51A738-CC97-4C29-BC02-5A281A5F141B</id></plugs></chargePointInfo></chargePointsInfo><plugsInfo><plugInfo><id>BEB2CB85-33DB-4261-8DD7-875E978E45DB.DD51A738-CC97-4C29-BC02-5A281A5F141C</id><name>EVSE.DC</name><number>1</number><supportedCurrent>-1</supportedCurrent><plugCurrent>-1</plugCurrent><EVCommDevice></EVCommDevice><hasCover>F</hasCover><hasLock>F</hasLock><meter>DC-Meter</meter><socketsNumber>2</socketsNumber><sockets><id>476A1CEA-951D-436A-A6CC-F71B94E48727</id><id>476A1CEA-951D-436A-A6CC-F71B94E48726</id></sockets></plugInfo><plugInfo><id>BEB2CB85-33DB-4261-8DD7-875E978E45DB.DD51A738-CC97-4C29-BC02-5A281A5F141B</id><name>EVSE.AC</name><number>2</number><chargeMode>3</chargeMode><connectorType>unknown</connectorType><supportedCurrent>63</supportedCurrent><plugCurrent>-1</plugCurrent><EVCommDevice></EVCommDevice><hasCover>F</hasCover><hasLock>F</hasLock><meter>AC-Meter</meter><socketsNumber>1</socketsNumber><sockets><id>476A1CEA-951D-436A-A6CC-F71B94E48725</id></sockets></plugInfo></plugsInfo><socketsInfo><socketInfo><id>BEB2CB85-33DB-4261-8DD7-875E978E45DB.DD51A738-CC97-4C29-BC02-5A281A5F141C.476A1CEA-951D-436A-A6CC-F71B94E48727</id><name>EVSE.DC.CCS</name><number>1</number><chargeMode>4</chargeMode><connectorType>CCS2</connectorType><supportedCurrent>-1</supportedCurrent><chargeEnergyLimit>0.000000</chargeEnergyLimit><maxPowerChargeComplete>100</maxPowerChargeComplete><maxTimeChargeComplete>900</maxTimeChargeComplete><stopChargeOnEvSideDisconnect>T</stopChargeOnEvSideDisconnect><unlockConnectorOnEvSideDisconnect>T</unlockConnectorOnEvSideDisconnect><EVCommDevice>DC-Mode 4</EVCommDevice><plugCurrent>-1.000000</plugCurrent><hasCover>F</hasCover><hasLock>F</hasLock><hasSafeStorageLock>F</hasSafeStorageLock><meter>DC-Meter</meter></socketInfo><socketInfo><id>BEB2CB85-33DB-4261-8DD7-875E978E45DB.DD51A738-CC97-4C29-BC02-5A281A5F141C.476A1CEA-951D-436A-A6CC-F71B94E48726</id><name>EVSE.DC.CHAdeMO</name><number>2</number><chargeMode>4</chargeMode><connectorType>CHAdeMO</connectorType><supportedCurrent>-1</supportedCurrent><chargeEnergyLimit>0.000000</chargeEnergyLimit><maxPowerChargeComplete>100</maxPowerChargeComplete><maxTimeChargeComplete>900</maxTimeChargeComplete><stopChargeOnEvSideDisconnect>T</stopChargeOnEvSideDisconnect><unlockConnectorOnEvSideDisconnect>T</unlockConnectorOnEvSideDisconnect><EVCommDevice>DC-Mode 4</EVCommDevice><plugCurrent>-1.000000</plugCurrent><hasCover>F</hasCover><hasLock>T</hasLock><hasSafeStorageLock>F</hasSafeStorageLock><meter>DC-Meter</meter></socketInfo><socketInfo><id>BEB2CB85-33DB-4261-8DD7-875E978E45DB.DD51A738-CC97-4C29-BC02-5A281A5F141B.476A1CEA-951D-436A-A6CC-F71B94E48725</id><name>EVSE.AC.AC</name><number>3</number><chargeMode>3</chargeMode><connectorType>62196 TYPE 2</connectorType><supportedCurrent>63</supportedCurrent><chargeEnergyLimit>0.000000</chargeEnergyLimit><maxPowerChargeComplete>100</maxPowerChargeComplete><maxTimeChargeComplete>900</maxTimeChargeComplete><stopChargeOnEvSideDisconnect>T</stopChargeOnEvSideDisconnect><unlockConnectorOnEvSideDisconnect>T</unlockConnectorOnEvSideDisconnect><EVCommDevice>AC-Mode 3</EVCommDevice><plugCurrent>63.000000</plugCurrent><hasCover>F</hasCover><hasLock>F</hasLock><hasSafeStorageLock>F</hasSafeStorageLock><meter>AC-Meter</meter></socketInfo></socketsInfo><chargesInfo><chargeInfo><id>BEB2CB85-33DB-4261-8DD7-875E978E45DB.DD51A738-CC97-4C29-BC02-5A281A5F141C</id><name>EVSE.DC</name><number>1</number><state>0</state><chargeId>FF4C1C14-8C2C-11EC-8C2C-11EC9D949334</chargeId><user></user><userType></userType><requestDate>1645291633.163000</requestDate><beginDate>-1.000000</beginDate><endDate>-1.000000</endDate><chargeTime>0</chargeTime><stopped>0</stopped><stoppedByError>F</stoppedByError><activeEnergy>178410.000000</activeEnergy><partialActiveEnergy>0.000000</partialActiveEnergy></chargeInfo><chargeInfo><id>BEB2CB85-33DB-4261-8DD7-875E978E45DB.DD51A738-CC97-4C29-BC02-5A281A5F141B</id><name>EVSE.AC</name><number>2</number><state>0</state><chargeId>00000000-0000-0000-0000-000000000000</chargeId><user>37B55D59</user><userType></userType><requestDate>1623336256.256000</requestDate><beginDate>1623336258.185000</beginDate><endDate>1645019656.289000</endDate><chargeTime>21080771</chargeTime><stopped>1</stopped><stoppedByError>F</stoppedByError><activeEnergy>30.000000</activeEnergy><partialActiveEnergy>0.000000</partialActiveEnergy></chargeInfo></chargesInfo></info>